<annotation verified="yes">
    <folder>Annotation</folder>
    <filename>15.png</filename>
    <path>Panoramic-X-Ray-PascalVOC-export/Annotations/15.png</path>
    <source>
        <database>Unknown</database>
    </source>
    <size>
        <width>3000</width>
        <height>1270</height>
        <depth>3</depth>
    </size>
    <segmented>0</segmented>
    <object>
    <name>tooth</name>
    <pose>Unspecified</pose>
    <truncated>0</truncated>
    <difficult>0</difficult>
    <bndbox>
        <xmin>642.7366619592755</xmin>
        <ymin>282.7998044849497</ymin>
        <xmax>779.9437504118587</xmax>
        <ymax>541.2953797061887</ymax>
    </bndbox>
</object><object>
    <name>tooth</name>
    <pose>Unspecified</pose>
    <truncated>0</truncated>
    <difficult>0</difficult>
    <bndbox>
        <xmin>728.2099343955015</xmin>
        <ymin>309.7731872153493</ymin>
        <xmax>878.9129427022318</xmax>
        <ymax>610.9767613368751</ymax>
    </bndbox>
</object><object>
    <name>tooth</name>
    <pose>Unspecified</pose>
    <truncated>0</truncated>
    <difficult>0</difficult>
    <bndbox>
        <xmin>876.6635083213743</xmin>
        <ymin>289.5431501675496</ymin>
        <xmax>1013.870768381707</xmax>
        <ymax>624.463452702075</ymax>
    </bndbox>
</object><object>
    <name>tooth</name>
    <pose>Unspecified</pose>
    <truncated>0</truncated>
    <difficult>0</difficult>
    <bndbox>
        <xmin>998.1255857544518</xmin>
        <ymin>323.2599643268416</ymin>
        <xmax>1110.5904404873477</xmax>
        <ymax>640.1979831256697</ymax>
    </bndbox>
</object><object>
    <name>tooth</name>
    <pose>Unspecified</pose>
    <truncated>0</truncated>
    <difficult>0</difficult>
    <bndbox>
        <xmin>1061.1059730479733</xmin>
        <ymin>338.9944947504364</ymin>
        <xmax>1196.0637987274486</xmax>
        <ymax>628.9590450725723</ymax>
    </bndbox>
</object><object>
    <name>tooth</name>
    <pose>Unspecified</pose>
    <truncated>0</truncated>
    <difficult>0</difficult>
    <bndbox>
        <xmin>1144.3298969072166</xmin>
        <ymin>323.2599643268416</ymin>
        <xmax>1288.2849452868734</xmax>
        <ymax>628.9590450725724</ymax>
    </bndbox>
</object><object>
    <name>tooth</name>
    <pose>Unspecified</pose>
    <truncated>0</truncated>
    <difficult>0</difficult>
    <bndbox>
        <xmin>1274.7891970404758</xmin>
        <ymin>325.5077176389441</ymin>
        <xmax>1378.2568290731901</xmax>
        <ymax>595.2422309132803</ymax>
    </bndbox>
</object><object>
    <name>tooth</name>
    <pose>Unspecified</pose>
    <truncated>0</truncated>
    <difficult>0</difficult>
    <bndbox>
        <xmin>1378.2568290731901</xmin>
        <ymin>300.7820882206469</ymin>
        <xmax>1497.4696437331597</xmax>
        <ymax>581.7555395480806</ymax>
    </bndbox>
</object><object>
    <name>tooth</name>
    <pose>Unspecified</pose>
    <truncated>0</truncated>
    <difficult>0</difficult>
    <bndbox>
        <xmin>1499.7189065062676</xmin>
        <ymin>287.2953111091546</ymin>
        <xmax>1621.1809839393452</xmax>
        <ymax>592.9944776011779</ymax>
    </bndbox>
</object><object>
    <name>tooth</name>
    <pose>Unspecified</pose>
    <truncated>0</truncated>
    <difficult>0</difficult>
    <bndbox>
        <xmin>1614.4330240122717</xmin>
        <ymin>285.04755779705215</ymin>
        <xmax>1724.6486159720598</xmax>
        <ymax>586.251131918578</ymax>
    </bndbox>
</object><object>
    <name>tooth</name>
    <pose>Unspecified</pose>
    <truncated>0</truncated>
    <difficult>0</difficult>
    <bndbox>
        <xmin>1720.149918818094</xmin>
        <ymin>285.04755779705215</ymin>
        <xmax>1841.6119962511716</xmax>
        <ymax>601.9855765958803</ymax>
    </bndbox>
</object><object>
    <name>tooth</name>
    <pose>Unspecified</pose>
    <truncated>0</truncated>
    <difficult>0</difficult>
    <bndbox>
        <xmin>1830.365510777882</xmin>
        <ymin>291.79090347965206</ymin>
        <xmax>1940.5811027376699</xmax>
        <ymax>597.4900699716753</ymax>
    </bndbox>
</object><object>
    <name>tooth</name>
    <pose>Unspecified</pose>
    <truncated>0</truncated>
    <difficult>0</difficult>
    <bndbox>
        <xmin>1915.8388690179827</xmin>
        <ymin>276.0563730560573</ymin>
        <xmax>2021.5557638238051</xmax>
        <ymax>601.9855765958803</ymax>
    </bndbox>
</object><object>
    <name>tooth</name>
    <pose>Unspecified</pose>
    <truncated>0</truncated>
    <difficult>0</difficult>
    <bndbox>
        <xmin>2017.0572382775892</xmin>
        <ymin>282.7998044849497</ymin>
        <xmax>2165.510812203462</xmax>
        <ymax>592.9944776011779</ymax>
    </bndbox>
</object><object>
    <name>tooth</name>
    <pose>Unspecified</pose>
    <truncated>0</truncated>
    <difficult>0</difficult>
    <bndbox>
        <xmin>2161.012286657246</xmin>
        <ymin>233.34845990206287</ymin>
        <xmax>2307.216426202261</xmax>
        <ymax>581.7555395480806</ymax>
    </bndbox>
</object><object>
    <name>tooth</name>
    <pose>Unspecified</pose>
    <truncated>0</truncated>
    <difficult>0</difficult>
    <bndbox>
        <xmin>2253.2334332166706</xmin>
        <ymin>204.12723811326828</ymin>
        <xmax>2408.4347954618675</xmax>
        <ymax>516.569664541599</ymax>
    </bndbox>
</object><object>
    <name>tooth</name>
    <pose>Unspecified</pose>
    <truncated>0</truncated>
    <difficult>0</difficult>
    <bndbox>
        <xmin>2320.7123460564085</xmin>
        <ymin>579.5077004896856</ymin>
        <xmax>2473.6646171362468</xmax>
        <ymax>817.7732386631249</ymax>
    </bndbox>
</object><object>
    <name>tooth</name>
    <pose>Unspecified</pose>
    <truncated>0</truncated>
    <difficult>0</difficult>
    <bndbox>
        <xmin>2152.0150639570643</xmin>
        <ymin>575.0121938654806</ymin>
        <xmax>2363.448853568709</xmax>
        <ymax>878.4634355528165</ymax>
    </bndbox>
</object><object>
    <name>tooth</name>
    <pose>Unspecified</pose>
    <truncated>0</truncated>
    <difficult>0</difficult>
    <bndbox>
        <xmin>1990.0655701770445</xmin>
        <ymin>599.7378232837777</ymin>
        <xmax>2172.2587721305354</xmax>
        <ymax>909.9324964000059</ymax>
    </bndbox>
</object><object>
    <name>tooth</name>
    <pose>Unspecified</pose>
    <truncated>0</truncated>
    <difficult>0</difficult>
    <bndbox>
        <xmin>1875.3514526710403</xmin>
        <ymin>608.7290080247727</ymin>
        <xmax>1992.3150045579018</xmax>
        <ymax>927.9148658819959</ymax>
    </bndbox>
</object><object>
    <name>tooth</name>
    <pose>Unspecified</pose>
    <truncated>0</truncated>
    <difficult>0</difficult>
    <bndbox>
        <xmin>1783.1303061116157</xmin>
        <ymin>610.9767613368751</ymin>
        <xmax>1891.0966352982957</xmax>
        <ymax>939.153803935093</ymax>
    </bndbox>
</object><object>
    <name>tooth</name>
    <pose>Unspecified</pose>
    <truncated>0</truncated>
    <difficult>0</difficult>
    <bndbox>
        <xmin>1675.1639769249357</xmin>
        <ymin>601.9855765958803</ymin>
        <xmax>1783.1303061116157</xmax>
        <ymax>943.6493105592981</ymax>
    </bndbox>
</object><object>
    <name>tooth</name>
    <pose>Unspecified</pose>
    <truncated>0</truncated>
    <difficult>0</difficult>
    <bndbox>
        <xmin>1585.192093138619</xmin>
        <ymin>608.7290080247727</ymin>
        <xmax>1675.1639769249357</xmax>
        <ymax>927.9148658819959</ymax>
    </bndbox>
</object><object>
    <name>tooth</name>
    <pose>Unspecified</pose>
    <truncated>0</truncated>
    <difficult>0</difficult>
    <bndbox>
        <xmin>1501.9681692793756</xmin>
        <ymin>635.7023907551722</ymin>
        <xmax>1621.1809839393452</xmax>
        <ymax>930.1626191940982</ymax>
    </bndbox>
</object><object>
    <name>tooth</name>
    <pose>Unspecified</pose>
    <truncated>0</truncated>
    <difficult>0</difficult>
    <bndbox>
        <xmin>1420.9935081932404</xmin>
        <ymin>635.7023907551722</ymin>
        <xmax>1506.4666948255915</xmax>
        <ymax>941.4015572471956</ymax>
    </bndbox>
</object><object>
    <name>tooth</name>
    <pose>Unspecified</pose>
    <truncated>0</truncated>
    <difficult>0</difficult>
    <bndbox>
        <xmin>1331.0216244069236</xmin>
        <ymin>633.4546374430698</ymin>
        <xmax>1418.7442454201323</xmax>
        <ymax>921.1714344531033</ymax>
    </bndbox>
</object><object>
    <name>tooth</name>
    <pose>Unspecified</pose>
    <truncated>0</truncated>
    <difficult>0</difficult>
    <bndbox>
        <xmin>1229.8032551473173</xmin>
        <ymin>617.720107019475</ymin>
        <xmax>1331.0216244069236</xmax>
        <ymax>948.1449886760879</ymax>
    </bndbox>
</object><object>
    <name>tooth</name>
    <pose>Unspecified</pose>
    <truncated>0</truncated>
    <difficult>0</difficult>
    <bndbox>
        <xmin>1135.3326742070349</xmin>
        <ymin>640.1979831256697</ymin>
        <xmax>1234.3017806935331</xmax>
        <ymax>939.153803935093</ymax>
    </bndbox>
</object><object>
    <name>tooth</name>
    <pose>Unspecified</pose>
    <truncated>0</truncated>
    <difficult>0</difficult>
    <bndbox>
        <xmin>1034.1143049474285</xmin>
        <ymin>635.7023907551722</ymin>
        <xmax>1139.8313713610005</xmax>
        <ymax>941.4015572471956</ymax>
    </bndbox>
</object><object>
    <name>tooth</name>
    <pose>Unspecified</pose>
    <truncated>0</truncated>
    <difficult>0</difficult>
    <bndbox>
        <xmin>867.6664572289421</xmin>
        <ymin>635.7023907551722</ymin>
        <xmax>1020.6185567010309</xmax>
        <ymax>950.3927419881904</ymax>
    </bndbox>
</object><object>
    <name>tooth</name>
    <pose>Unspecified</pose>
    <truncated>0</truncated>
    <difficult>0</difficult>
    <bndbox>
        <xmin>674.2268556060362</xmin>
        <ymin>604.2334156542752</ymin>
        <xmax>885.6607310215558</xmax>
        <ymax>916.6759278288984</ymax>
    </bndbox>
</object>
</annotation>
