<annotation verified="yes">
    <folder>Annotation</folder>
    <filename>77.png</filename>
    <path>Panoramic-X-Ray-PascalVOC-export/Annotations/77.png</path>
    <source>
        <database>Unknown</database>
    </source>
    <size>
        <width>2950</width>
        <height>1100</height>
        <depth>3</depth>
    </size>
    <segmented>0</segmented>
    <object>
    <name>tooth</name>
    <pose>Unspecified</pose>
    <truncated>0</truncated>
    <difficult>0</difficult>
    <bndbox>
        <xmin>611.5772251674107</xmin>
        <ymin>289.97315950920245</ymin>
        <xmax>749.1314697265625</xmax>
        <ymax>543.7154290134921</ymax>
    </bndbox>
</object><object>
    <name>tooth</name>
    <pose>Unspecified</pose>
    <truncated>0</truncated>
    <difficult>0</difficult>
    <bndbox>
        <xmin>746.4343680245536</xmin>
        <ymin>262.9792944785276</ymin>
        <xmax>881.2915108816965</xmax>
        <ymax>568.0099487304688</ymax>
    </bndbox>
</object><object>
    <name>tooth</name>
    <pose>Unspecified</pose>
    <truncated>0</truncated>
    <difficult>0</difficult>
    <bndbox>
        <xmin>875.897101702009</xmin>
        <ymin>268.3779851059241</ymin>
        <xmax>1029.6343680245536</xmax>
        <ymax>581.5068812458062</ymax>
    </bndbox>
</object><object>
    <name>tooth</name>
    <pose>Unspecified</pose>
    <truncated>0</truncated>
    <difficult>0</difficult>
    <bndbox>
        <xmin>1005.3600411551339</xmin>
        <ymin>249.4823619631902</ymin>
        <xmax>1118.639958844866</xmax>
        <ymax>565.3105004433475</ymax>
    </bndbox>
</object><object>
    <name>tooth</name>
    <pose>Unspecified</pose>
    <truncated>0</truncated>
    <difficult>0</difficult>
    <bndbox>
        <xmin>1167.1886125837054</xmin>
        <ymin>230.58663584703316</ymin>
        <xmax>1285.8629394531251</xmax>
        <ymax>568.0099487304688</ymax>
    </bndbox>
</object><object>
    <name>tooth</name>
    <pose>Unspecified</pose>
    <truncated>0</truncated>
    <difficult>0</difficult>
    <bndbox>
        <xmin>1285.862939453125</xmin>
        <ymin>235.98542944785277</ymin>
        <xmax>1382.960041155134</xmax>
        <ymax>541.0160836997939</ymax>
    </bndbox>
</object><object>
    <name>tooth</name>
    <pose>Unspecified</pose>
    <truncated>0</truncated>
    <difficult>0</difficult>
    <bndbox>
        <xmin>1374.8685302734375</xmin>
        <ymin>225.1878422462136</ymin>
        <xmax>1496.2399588448661</xmax>
        <ymax>546.4148773006135</ymax>
    </bndbox>
</object><object>
    <name>tooth</name>
    <pose>Unspecified</pose>
    <truncated>0</truncated>
    <difficult>0</difficult>
    <bndbox>
        <xmin>1501.6343680245536</xmin>
        <ymin>227.8871875599118</ymin>
        <xmax>1639.1886125837054</xmax>
        <ymax>541.0160836997939</ymax>
    </bndbox>
</object><object>
    <name>tooth</name>
    <pose>Unspecified</pose>
    <truncated>0</truncated>
    <difficult>0</difficult>
    <bndbox>
        <xmin>1633.7944091796876</xmin>
        <ymin>219.789048645394</ymin>
        <xmax>1747.0743268694198</xmax>
        <ymax>535.6172900989743</ymax>
    </bndbox>
</object><object>
    <name>tooth</name>
    <pose>Unspecified</pose>
    <truncated>0</truncated>
    <difficult>0</difficult>
    <bndbox>
        <xmin>1722.8</xmin>
        <ymin>219.789048645394</ymin>
        <xmax>1844.1714285714286</xmax>
        <ymax>549.1142226143118</ymax>
    </bndbox>
</object><object>
    <name>tooth</name>
    <pose>Unspecified</pose>
    <truncated>0</truncated>
    <difficult>0</difficult>
    <bndbox>
        <xmin>1811.8057965959822</xmin>
        <ymin>214.3902550445744</ymin>
        <xmax>1922.3886125837055</xmax>
        <ymax>559.911809815951</ymax>
    </bndbox>
</object><object>
    <name>tooth</name>
    <pose>Unspecified</pose>
    <truncated>0</truncated>
    <difficult>0</difficult>
    <bndbox>
        <xmin>1989.8171840122768</xmin>
        <ymin>254.88105259058665</ymin>
        <xmax>2124.674532645089</xmax>
        <ymax>562.6111551296492</ymax>
    </bndbox>
</object><object>
    <name>tooth</name>
    <pose>Unspecified</pose>
    <truncated>0</truncated>
    <difficult>0</difficult>
    <bndbox>
        <xmin>2124.674532645089</xmin>
        <ymin>227.8871875599118</ymin>
        <xmax>2256.8343680245534</xmax>
        <ymax>543.7154290134922</ymax>
    </bndbox>
</object><object>
    <name>tooth</name>
    <pose>Unspecified</pose>
    <truncated>0</truncated>
    <difficult>0</difficult>
    <bndbox>
        <xmin>2248.7428571428572</xmin>
        <ymin>246.78291367606883</ymin>
        <xmax>2386.2973074776787</xmax>
        <ymax>543.7154290134921</ymax>
    </bndbox>
</object><object>
    <name>tooth</name>
    <pose>Unspecified</pose>
    <truncated>0</truncated>
    <difficult>0</difficult>
    <bndbox>
        <xmin>2100.4</xmin>
        <ymin>538.3166354126726</ymin>
        <xmax>2308.079917689732</xmax>
        <ymax>810.9547340065424</ymax>
    </bndbox>
</object><object>
    <name>tooth</name>
    <pose>Unspecified</pose>
    <truncated>0</truncated>
    <difficult>0</difficult>
    <bndbox>
        <xmin>1962.8457554408483</xmin>
        <ymin>568.0099487304688</ymin>
        <xmax>2157.040164620536</xmax>
        <ymax>848.7461862388564</ymax>
    </bndbox>
</object><object>
    <name>tooth</name>
    <pose>Unspecified</pose>
    <truncated>0</truncated>
    <difficult>0</difficult>
    <bndbox>
        <xmin>1890.0229806082589</xmin>
        <ymin>565.3105004433475</ymin>
        <xmax>1962.8457554408483</xmax>
        <ymax>843.3472896646138</ymax>
    </bndbox>
</object><object>
    <name>tooth</name>
    <pose>Unspecified</pose>
    <truncated>0</truncated>
    <difficult>0</difficult>
    <bndbox>
        <xmin>1803.7142857142858</xmin>
        <ymin>559.911809815951</ymin>
        <xmax>1887.3256731305805</xmax>
        <ymax>864.9424640678922</ymax>
    </bndbox>
</object><object>
    <name>tooth</name>
    <pose>Unspecified</pose>
    <truncated>0</truncated>
    <difficult>0</difficult>
    <bndbox>
        <xmin>1690.4343680245536</xmin>
        <ymin>562.6111551296492</ymin>
        <xmax>1779.4399588448662</xmax>
        <ymax>902.7339163002061</ymax>
    </bndbox>
</object><object>
    <name>tooth</name>
    <pose>Unspecified</pose>
    <truncated>0</truncated>
    <difficult>0</difficult>
    <bndbox>
        <xmin>1590.639958844866</xmin>
        <ymin>562.6111551296492</ymin>
        <xmax>1676.9486537388393</xmax>
        <ymax>891.936329098567</ymax>
    </bndbox>
</object><object>
    <name>tooth</name>
    <pose>Unspecified</pose>
    <truncated>0</truncated>
    <difficult>0</difficult>
    <bndbox>
        <xmin>1512.422980608259</xmin>
        <ymin>570.709294044167</ymin>
        <xmax>1587.942857142857</xmax>
        <ymax>867.6418093815903</ymax>
    </bndbox>
</object><object>
    <name>tooth</name>
    <pose>Unspecified</pose>
    <truncated>0</truncated>
    <difficult>0</difficult>
    <bndbox>
        <xmin>1439.6</xmin>
        <ymin>557.2123615288295</ymin>
        <xmax>1507.0285714285712</xmax>
        <ymax>864.942464067892</ymax>
    </bndbox>
</object><object>
    <name>tooth</name>
    <pose>Unspecified</pose>
    <truncated>0</truncated>
    <difficult>0</difficult>
    <bndbox>
        <xmin>1355.9886125837054</xmin>
        <ymin>562.6111551296492</ymin>
        <xmax>1428.8113874162946</xmax>
        <ymax>875.7400512695312</ymax>
    </bndbox>
</object><object>
    <name>tooth</name>
    <pose>Unspecified</pose>
    <truncated>0</truncated>
    <difficult>0</difficult>
    <bndbox>
        <xmin>1231.9200823102678</xmin>
        <ymin>562.6111551296492</ymin>
        <xmax>1337.1086948939733</xmax>
        <ymax>864.9424640678922</ymax>
    </bndbox>
</object><object>
    <name>tooth</name>
    <pose>Unspecified</pose>
    <truncated>0</truncated>
    <difficult>0</difficult>
    <bndbox>
        <xmin>1134.8229806082588</xmin>
        <ymin>562.6111551296492</ymin>
        <xmax>1234.6171840122768</xmax>
        <ymax>867.6418093815903</ymax>
    </bndbox>
</object><object>
    <name>tooth</name>
    <pose>Unspecified</pose>
    <truncated>0</truncated>
    <difficult>0</difficult>
    <bndbox>
        <xmin>1040.422980608259</xmin>
        <ymin>573.4087423312884</ymin>
        <xmax>1137.520082310268</xmax>
        <ymax>881.1387418969277</ymax>
    </bndbox>
</object><object>
    <name>tooth</name>
    <pose>Unspecified</pose>
    <truncated>0</truncated>
    <difficult>0</difficult>
    <bndbox>
        <xmin>846.2285714285714</xmin>
        <ymin>581.5068812458062</ymin>
        <xmax>1059.302898297991</xmax>
        <ymax>875.7400512695312</ymax>
    </bndbox>
</object><object>
    <name>tooth</name>
    <pose>Unspecified</pose>
    <truncated>0</truncated>
    <difficult>0</difficult>
    <bndbox>
        <xmin>687.0971017020089</xmin>
        <ymin>557.2123615288295</ymin>
        <xmax>897.4743268694197</xmax>
        <ymax>856.8442221799511</ymax>
    </bndbox>
</object><object>
    <name>tooth</name>
    <pose>Unspecified</pose>
    <truncated>0</truncated>
    <difficult>0</difficult>
    <bndbox>
        <xmin>565.7256731305804</xmin>
        <ymin>514.0222186691191</ymin>
        <xmax>749.1314697265625</xmax>
        <ymax>773.1632817742284</ymax>
    </bndbox>
</object>
</annotation>
